cronico/__init__.py
cronico/main.py
cronico-0.9.16.dist-info/licenses/LICENSE
cronico-0.9.16.dist-info/METADATA
cronico-0.9.16.dist-info/WHEEL
cronico-0.9.16.dist-info/entry_points.txt
cronico-0.9.16.dist-info/top_level.txt
cronico-0.9.16.dist-info/RECORD
