Metadata-Version: 2.4
Name: cronico
Version: 0.9.16
Summary: Another YAML-based scheduler
Author-email: Luis Medel <luis@luismedel.com>
License: MIT
Project-URL: Homepage, https://github.com/luismedel/cronico
Project-URL: Issues, https://github.com/luismedel/cronico/issues
Classifier: Programming Language :: Python :: 3
Classifier: License :: OSI Approved :: MIT License
Classifier: Operating System :: OS Independent
Requires-Python: >=3.8
License-File: LICENSE
Requires-Dist: PyYAML==6.0.2
Requires-Dist: croniter==6.0.0
Requires-Dist: python-dotenv==1.1.1
Provides-Extra: dev
Requires-Dist: mypy==1.18.1; extra == "dev"
Requires-Dist: ruff==0.13.0; extra == "dev"
Requires-Dist: types-PyYAML==6.0.12.20250822; extra == "dev"
Requires-Dist: types-croniter==6.0.0.20250809; extra == "dev"
Requires-Dist: build; extra == "dev"
Requires-Dist: twine; extra == "dev"
Dynamic: license-file
